waf_http_api/__init__.py
waf_http_api/py.typed
waf_http_api/_jsii/__init__.py
waf_http_api/_jsii/waf-http-api@1.2.0.jsii.tgz
waf_http_api-1.2.0.dist-info/LICENSE
waf_http_api-1.2.0.dist-info/METADATA
waf_http_api-1.2.0.dist-info/WHEEL
waf_http_api-1.2.0.dist-info/top_level.txt
waf_http_api-1.2.0.dist-info/RECORD
